{"config":{"bar_type":"time_5s","target_ticks":18,"stop_ticks":5,"take_profit_ticks":20,"volume_horizon":500,"max_time_horizon_s":300},"costs":{"commission_per_side":0.62,"fixed_spread_ticks":1,"slippage_ticks":0,"contract_multiplier":5,"tick_size":0.25},"days_processed":19,"days_skipped":0,"first_to_hit":{"total_trades":3053,"winning_trades":1156,"losing_trades":1897,"win_rate":0.378644,"gross_pnl":12858.8,"net_pnl":5256.79,"expectancy":1.72184,"profit_factor":1.83682,"sharpe":0.107379,"max_drawdown":410.947,"trades_per_day":160.684,"avg_bars_held":0,"avg_duration_s":0,"hold_fraction":0,"exit_reasons":{"target":716,"stop":1890,"take_profit":430,"expiry":0,"session_end":17,"safety_cap":0}},"triple_barrier":{"total_trades":2682,"winning_trades":1239,"losing_trades":1443,"win_rate":0.461969,"gross_pnl":18921.2,"net_pnl":12243.1,"expectancy":4.56491,"profit_factor":2.63989,"sharpe":0.276471,"max_drawdown":255.547,"trades_per_day":141.158,"avg_bars_held":0,"avg_duration_s":0,"hold_fraction":0,"exit_reasons":{"target":753,"stop":1436,"take_profit":477,"expiry":0,"session_end":16,"safety_cap":0}},"per_quarter":{"Q1":{"first_to_hit":{"total_trades":1035,"winning_trades":444,"losing_trades":591,"win_rate":0.428986,"gross_pnl":5871.25,"net_pnl":3294.1,"expectancy":3.18271,"profit_factor":2.13113,"sharpe":0.187957,"max_drawdown":187.715,"trades_per_day":258.75,"avg_bars_held":0,"avg_duration_s":0,"hold_fraction":0,"exit_reasons":{"target":225,"stop":591,"take_profit":216,"expiry":0,"session_end":3,"safety_cap":0}},"triple_barrier":{"total_trades":916,"winning_trades":453,"losing_trades":463,"win_rate":0.494541,"gross_pnl":7320,"net_pnl":5039.17,"expectancy":5.50127,"profit_factor":2.81076,"sharpe":0.319993,"max_drawdown":121.1,"trades_per_day":229,"avg_bars_held":0,"avg_duration_s":0,"hold_fraction":0,"exit_reasons":{"target":226,"stop":463,"take_profit":224,"expiry":0,"session_end":3,"safety_cap":0}}},"Q2":{"first_to_hit":{"total_trades":715,"winning_trades":257,"losing_trades":458,"win_rate":0.359441,"gross_pnl":2671.88,"net_pnl":891.525,"expectancy":1.24689,"profit_factor":1.76014,"sharpe":0.0805683,"max_drawdown":364.784,"trades_per_day":143,"avg_bars_held":0,"avg_duration_s":0,"hold_fraction":0,"exit_reasons":{"target":176,"stop":456,"take_profit":78,"expiry":0,"session_end":5,"safety_cap":0}},"triple_barrier":{"total_trades":611,"winning_trades":271,"losing_trades":340,"win_rate":0.443535,"gross_pnl":3982.5,"net_pnl":2461.11,"expectancy":4.02801,"profit_factor":2.53026,"sharpe":0.250574,"max_drawdown":147.06,"trades_per_day":122.2,"avg_bars_held":0,"avg_duration_s":0,"hold_fraction":0,"exit_reasons":{"target":181,"stop":336,"take_profit":89,"expiry":0,"session_end":5,"safety_cap":0}}},"Q3":{"first_to_hit":{"total_trades":673,"winning_trades":250,"losing_trades":423,"win_rate":0.371471,"gross_pnl":2591.25,"net_pnl":915.48,"expectancy":1.3603,"profit_factor":1.76101,"sharpe":0.0862476,"max_drawdown":373.639,"trades_per_day":134.6,"avg_bars_held":0,"avg_duration_s":0,"hold_fraction":0,"exit_reasons":{"target":171,"stop":421,"take_profit":76,"expiry":0,"session_end":5,"safety_cap":0}},"triple_barrier":{"total_trades":615,"winning_trades":282,"losing_trades":333,"win_rate":0.458537,"gross_pnl":4283.75,"net_pnl":2752.4,"expectancy":4.47545,"profit_factor":2.66886,"sharpe":0.276458,"max_drawdown":255.529,"trades_per_day":123,"avg_bars_held":0,"avg_duration_s":0,"hold_fraction":0,"exit_reasons":{"target":192,"stop":331,"take_profit":88,"expiry":0,"session_end":4,"safety_cap":0}}},"Q4":{"first_to_hit":{"total_trades":630,"winning_trades":205,"losing_trades":425,"win_rate":0.325397,"gross_pnl":1724.38,"net_pnl":155.675,"expectancy":0.247104,"profit_factor":1.52966,"sharpe":0.0162036,"max_drawdown":332.76,"trades_per_day":126,"avg_bars_held":0,"avg_duration_s":0,"hold_fraction":0,"exit_reasons":{"target":144,"stop":422,"take_profit":60,"expiry":0,"session_end":4,"safety_cap":0}},"triple_barrier":{"total_trades":540,"winning_trades":233,"losing_trades":307,"win_rate":0.431481,"gross_pnl":3335,"net_pnl":1990.4,"expectancy":3.68593,"profit_factor":2.43364,"sharpe":0.228281,"max_drawdown":124.64,"trades_per_day":108,"avg_bars_held":0,"avg_duration_s":0,"hold_fraction":0,"exit_reasons":{"target":154,"stop":306,"take_profit":76,"expiry":0,"session_end":4,"safety_cap":0}}}}}